googletrans_di/__init__.py
googletrans_di/client.py
googletrans_di/constants.py
googletrans_di/gtoken.py
googletrans_di/models.py
googletrans_di/urls.py
googletrans_di/utils.py
googletrans_di-4.0.2.dist-info/METADATA
googletrans_di-4.0.2.dist-info/WHEEL
googletrans_di-4.0.2.dist-info/licenses/LICENSE
googletrans_di-4.0.2.dist-info/RECORD
