Metadata-Version: 2.3
Name: googletrans-di
Version: 4.0.2
Summary: Free Google Translate API for Python. Translates totally free of charge.
Project-URL: Homepage, https://github.com/ssut/py-googletrans
Author-email: Jandre <j.badenhorst@decisioninc.com>, Ashwin T <ssut@ssut.me>
License: MIT
Classifier: Development Status :: 5 - Production/Stable
Classifier: Intended Audience :: Education
Classifier: Intended Audience :: End Users/Desktop
Classifier: License :: Freeware
Classifier: Operating System :: MacOS :: MacOS X
Classifier: Operating System :: Microsoft :: Windows
Classifier: Operating System :: POSIX
Classifier: Programming Language :: Python
Classifier: Programming Language :: Python :: 3.6
Classifier: Programming Language :: Python :: 3.7
Classifier: Programming Language :: Python :: 3.8
Classifier: Topic :: Education
Requires-Python: >=3.8
